semversion/__init__.py
semversion/__main__.py
semversion/constants.py
semversion/increment.py
semversion/initialize.py
semversion/version.py
semversion-2.0.3.dist-info/LICENSE
semversion-2.0.3.dist-info/METADATA
semversion-2.0.3.dist-info/WHEEL
semversion-2.0.3.dist-info/entry_points.txt
semversion-2.0.3.dist-info/top_level.txt
semversion-2.0.3.dist-info/RECORD
