Metadata-Version: 2.1
Name: semversion
Version: 2.0.3
Summary: Manage project semantic version.
Home-page: https://github.com/gadc1996/semversion
Author: Gabriel Delgado
Author-email: gadc1996@gmail.com
Classifier: Programming Language :: Python :: 3
Classifier: License :: OSI Approved :: MIT License
Classifier: Operating System :: OS Independent
License-File: LICENSE
Requires-Dist: click
